MANIFEST.in
README.md
requirements.txt
setup.cfg
setup.py
factorization/__init__.py
factorization/base.py
factorization/algorithms/ICA.py
factorization/algorithms/NMF.py
factorization/algorithms/PCA.py
factorization/algorithms/SVD.py
factorization/algorithms/__init__.py
test/test_algorithms.py
test/test_shaping.py
thunder_factorization.egg-info/PKG-INFO
thunder_factorization.egg-info/SOURCES.txt
thunder_factorization.egg-info/dependency_links.txt
thunder_factorization.egg-info/requires.txt
thunder_factorization.egg-info/top_level.txt